dynex/__init__.py
dynex/api.py
dynex/config.py
dynex/dynex_circuit.py
dynex/models.py
dynex/sampler.py
dynex/utils.py
dynex/interfaces/__init__.py
dynex/interfaces/api.py
dynex_nightly-0.1.28.dist-info/METADATA
dynex_nightly-0.1.28.dist-info/WHEEL
dynex_nightly-0.1.28.dist-info/top_level.txt
dynex_nightly-0.1.28.dist-info/RECORD
