Metadata-Version: 2.4
Name: dynex-nightly
Version: 0.1.28
Summary: Dynex SDK (beta) Neuromorphic Computing Library
Author: Dynex Developers
License-Expression: BSD-3-Clause
Keywords: neuromorphic,quantum,sdk,dynex,computing
Requires-Python: >=3.11
Requires-Dist: requests>=2.25
Requires-Dist: numpy>=1.23
Requires-Dist: dimod>=0.10.17
Requires-Dist: pyqubo>=1.2.0
Requires-Dist: tabulate>=0.8
Requires-Dist: tqdm>=4.66
Requires-Dist: pycryptodome>=3.18
Requires-Dist: pennylane>=0.34
Requires-Dist: ipython>=8.0
Requires-Dist: pydantic>=2.11.7
Requires-Dist: sympy>=1.12
Provides-Extra: dev
Requires-Dist: pytest>=7.0.0; extra == "dev"
Requires-Dist: pytest-cov>=4.0.0; extra == "dev"
Requires-Dist: pytest-xdist>=3.0.0; extra == "dev"
Requires-Dist: pytest-mock>=3.10.0; extra == "dev"
Requires-Dist: pytest-timeout>=2.1.0; extra == "dev"
Requires-Dist: flake8>=6.0.0; extra == "dev"
Requires-Dist: black>=23.0.0; extra == "dev"
Requires-Dist: isort>=5.12.0; extra == "dev"
Requires-Dist: mypy>=1.0.0; extra == "dev"
Requires-Dist: pre-commit>=3.0.0; extra == "dev"
Requires-Dist: coverage>=7.0.0; extra == "dev"
Requires-Dist: matplotlib>=3.6.0; extra == "dev"
Requires-Dist: networkx>=3.0.0; extra == "dev"
